pythonic_fp/gadgets/__init__.py
pythonic_fp/gadgets/__init__.pyi
pythonic_fp/gadgets/box.py
pythonic_fp/gadgets/box.pyi
pythonic_fp/gadgets/py.typed
pythonic_fp/gadgets/wrap.py
pythonic_fp/gadgets/wrap.pyi
pythonic_fp/gadgets/sentinels/__init__.py
pythonic_fp/gadgets/sentinels/__init__.pyi
pythonic_fp/gadgets/sentinels/flavored.py
pythonic_fp/gadgets/sentinels/flavored.pyi
pythonic_fp/gadgets/sentinels/novalue.py
pythonic_fp/gadgets/sentinels/novalue.pyi
pythonic_fp_gadgets-4.0.2.dist-info/licenses/LICENSE
pythonic_fp_gadgets-4.0.2.dist-info/WHEEL
pythonic_fp_gadgets-4.0.2.dist-info/METADATA
pythonic_fp_gadgets-4.0.2.dist-info/RECORD
