Metadata-Version: 2.4
Name: pythonic-fp-gadgets
Version: 4.0.2
Summary: Gadgets
Keywords: gadgets
Author-email: "Geoffrey R. Scheller" <geoffrey@scheller.com>
Requires-Python: >=3.13
Classifier: Development Status :: 4 - Beta
Classifier: Framework :: Pytest
Classifier: Intended Audience :: Developers
Classifier: License :: OSI Approved :: Apache Software License
Classifier: Operating System :: OS Independent
Classifier: Programming Language :: Python :: 3.13
Classifier: Typing :: Typed
License-File: LICENSE
Requires-Dist: pytest>=8.4.1 ; extra == "test"
Requires-Dist: pythonic-fp-circulararray>=6.0.1 ; extra == "test"
Project-URL: Changelog, https://github.com/grscheller/pythonic-fp-gadgets/blob/main/CHANGELOG.rst
Project-URL: Documentation, https://grscheller.github.io/pythonic-fp/gadgets/development/build/html/
Project-URL: Homepage, https://grscheller.github.io/pythonic-fp/homepage/build/html/
Project-URL: Source, https://github.com/grscheller/pythonic-fp-gadgets
Provides-Extra: test
